LICENSE
MANIFEST.in
README.md
package_info.json
requirements.txt
setup.py
th2_data_services/__init__.py
th2_data_services/data.py
th2_data_services/decode_error_handler.py
th2_data_services/filter.py
th2_data_services/sse_client.py
th2_data_services/th2_gui_report.py
th2_data_services.egg-info/PKG-INFO
th2_data_services.egg-info/SOURCES.txt
th2_data_services.egg-info/dependency_links.txt
th2_data_services.egg-info/requires.txt
th2_data_services.egg-info/top_level.txt
th2_data_services/events_tree/__init__.py
th2_data_services/events_tree/events_tree.py
th2_data_services/events_tree/exceptions.py
th2_data_services/interfaces/__init__.py
th2_data_services/interfaces/adapter.py
th2_data_services/interfaces/command.py
th2_data_services/interfaces/data_source.py
th2_data_services/interfaces/source_api.py
th2_data_services/interfaces/events_tree/__init__.py
th2_data_services/interfaces/events_tree/events_tree_collection.py
th2_data_services/interfaces/events_tree/parent_events_tree_collection.py
th2_data_services/interfaces/utils/__init__.py
th2_data_services/interfaces/utils/converter.py
th2_data_services/provider/__init__.py
th2_data_services/provider/command.py
th2_data_services/provider/exceptions.py
th2_data_services/provider/adapters/__init__.py
th2_data_services/provider/adapters/adapter_sse.py
th2_data_services/provider/interfaces/__init__.py
th2_data_services/provider/interfaces/command.py
th2_data_services/provider/interfaces/data_source.py
th2_data_services/provider/interfaces/filter.py
th2_data_services/provider/interfaces/source_api.py
th2_data_services/provider/interfaces/struct.py
th2_data_services/provider/interfaces/stub_builder.py
th2_data_services/provider/v5/__init__.py
th2_data_services/provider/v5/command_resolver.py
th2_data_services/provider/v5/struct.py
th2_data_services/provider/v5/stub_builder.py
th2_data_services/provider/v5/adapters/__init__.py
th2_data_services/provider/v5/adapters/basic_adapters.py
th2_data_services/provider/v5/adapters/event_adapters.py
th2_data_services/provider/v5/adapters/message_adapters.py
th2_data_services/provider/v5/commands/__init__.py
th2_data_services/provider/v5/commands/grpc.py
