Metadata-Version: 2.1
Name: th2-data-services
Version: 1.1.1
Summary: th2_data_services
Home-page: https://github.com/th2-net/th2-data-services
Author: TH2-devs
Author-email: th2-devs@exactprosystems.com
License: Apache License 2.0
Platform: UNKNOWN
Requires-Python: >=3.7
License-File: LICENSE
